async_google_trans_new/__init__.py
async_google_trans_new/__main__.py
async_google_trans_new/constant.py
async_google_trans_new/main.py
async_google_trans_new-1.4.6.dist-info/LICENSE
async_google_trans_new-1.4.6.dist-info/METADATA
async_google_trans_new-1.4.6.dist-info/WHEEL
async_google_trans_new-1.4.6.dist-info/top_level.txt
async_google_trans_new-1.4.6.dist-info/RECORD
