Metadata-Version: 2.1
Name: async-google-trans-new
Version: 1.4.6
Summary: google_trans_new but it is async!
Home-page: https://github.com/sevenc-nanashi/async_google_trans_new
Author: sevenc_nanashi
License: UNKNOWN
Platform: UNKNOWN
Classifier: Programming Language :: Python :: 3.8
Classifier: License :: OSI Approved :: MIT License
Classifier: Operating System :: OS Independent
License-File: LICENSE
Requires-Dist: aiohttp (<3.9.0,>=3.6.0)
Requires-Dist: urllib3
Requires-Dist: debtcollector
